{
	"recommendEvaluation": [{
			"pic": "img/index/evaluation1.png",
			"title": "如果有妹妹就好了",
			"score": "5.0",
			"picHead": "img/index/headPic.png",
			"username": "BLUE",
			"time": "2017-12-19",
			"textTitle": "如果能被认可就好了",
			"textContent": "其实看完了这不番剧之后有一个想法，那就是追番不能够真正地去体味作者的想法。只有在一种把番剧当做观看的心态的时候，可能体悟才会更深。..."
		},
		{
			"pic": "img/index/evaluation1.png",
			"title": "如果有妹妹就好了",
			"score": "1.0",
			"picHead": "img/index/headPic.png",
			"username": "BLUE",
			"time": "2017-12-19",
			"textTitle": "王大葱的一天",
			"textContent": "王大葱天天吃肉"
		}
	],
	"evaluation1": [{
			"pic": "img/index/evaluation1.png",
			"title": "如果有妹妹就好了",
			"score": "5.0",
			"picHead": "img/index/headPic.png",
			"username": "BLUE",
			"time": "2017-12-19",
			"textTitle": "如果能被认可就好了",
			"textContent": "其有一个想法，那就是追番不能够真正地去体味作者的想法。只有在一种把番剧当做观看的心态的时候，可能体悟才会更深。..."
		},
		{
			"pic": "img/index/evaluation1.png",
			"title": "如果有妹妹就好了",
			"score": "1.0",
			"picHead": "img/index/headPic.png",
			"username": "BLUE",
			"time": "2017-12-19",
			"textTitle": "王大葱的一天",
			"textContent": "王大葱天天吃肉"
		}
	],
	"evaluation2": [{
			"pic": "img/index/evaluation1.png",
			"title": "如果有妹妹就好了",
			"score": "5.0",
			"picHead": "img/index/headPic.png",
			"username": "BLUE",
			"time": "2017-12-19",
			"textTitle": "如果能被认可就好了",
			"textContent": "其实看完了这不番剧之后有一个想法，那就是追番不能够真正地去体味作者的想法。只有在一种把番剧当做观看的心态的时候，可能体悟才会更深。..."
		},
		{
			"pic": "img/index/evaluation1.png",
			"title": "如果有妹妹就好了",
			"score": "1.0",
			"picHead": "img/index/headPic.png",
			"username": "BLUE",
			"time": "2017-12-19",
			"textTitle": "王大葱的一天",
			"textContent": "王大葱天天吃肉"
		}
	],
	"evaluation3": [{
			"pic": "img/index/evaluation1.png",
			"title": "如果有妹妹就好了",
			"score": "5.0",
			"picHead": "img/index/headPic.png",
			"username": "BLUE",
			"time": "2017-12-19",
			"textTitle": "如果能被认可就好了",
			"textContent": "其实看完了这不番剧之后有一个想法，那就是追番不能够真正地去体味作者的想法。只有在一种把番剧当做观看的心态的时候，可能体悟才会更深。..."
		},
		{
			"pic": "img/index/evaluation1.png",
			"title": "如果就好了",
			"score": "1.0",
			"picHead": "img/index/headPic.png",
			"username": "BLUE",
			"time": "2017-12-19",
			"textTitle": "王大葱的一天",
			"textContent": "王大葱天天吃肉"
		}
	],
	"evaluation4": [{
			"pic": "img/index/evaluation1.png",
			"title": "如果有妹妹就好了",
			"score": "5.0",
			"picHead": "img/index/headPic.png",
			"username": "BLUE",
			"time": "2017-12-19",
			"textTitle": "如果能被认可就好了",
			"textContent": "其实看完了这不番剧之后有一个想法，那就是追番不能够真正地去体味作者的想法。只有在一种把番剧当做观看的心态的时候，可能体悟才会更深。..."
		},
		{
			"pic": "img/index/evaluation1.png",
			"title": "如果有妹妹就好了",
			"score": "1.0",
			"picHead": "img/index/headPic.png",
			"username": "BLUE",
			"time": "2017-12-19",
			"textTitle": "王大葱的一天",
			"textContent": "王大葱天天吃肉"
		}
	],
	"evaluation5": [{
			"pic": "img/index/evaluation1.png",
			"title": "如果有妹妹",
			"score": "5.0",
			"picHead": "img/index/headPic.png",
			"username": "BLUE",
			"time": "2017-12-19",
			"textTitle": "如果能被认可就好了",
			"textContent": "其实看完了这不番剧之后有一个想法，那就是追番不能够真正地去体味作者的想法。只有在一种把番剧当做观看的心态的时候，可能体悟才会更深。..."
		},
		{
			"pic": "img/index/evaluation1.png",
			"title": "如果有妹妹就好了",
			"score": "1.0",
			"picHead": "img/index/headPic.png",
			"username": "BLUE",
			"time": "2017-12-19",
			"textTitle": "王大葱的一天",
			"textContent": "王大葱天天吃肉"
		}
	]
}
